Workbook

Sheet Company Task Register
A1: Document Reference: IP-02-01-29
B2: Task Matrix
B5: Section Owners | N5: Tasks Section 1 - Introduction, Quality Management & Procedure Control | U5: Tasks Section 2 - Sales, Marketing | Y5: Tasks Section 3 - Estimating, Purchasing | AC5: Tasks Section 4 - Design, Project Management | AI5: Tasks Section 5 - High Voltage Electrical, Manufacturing | AL5: Tasks Section 6 - Commercial, Accounting | AQ5: Tasks Section 7 - Environmental, Health & Safety | AU5: Tasks Section 8 - Human Resources, Apprentices, Training | AW5: Tasks Section 9 - Company Engineers & Subcontractors, Vehicles, Company & Hire Equipment | AZ5: Tasks Section 10 - Information Technology, Cyber Security, Data Protection | BF5: Tasks Section 11 - Software Development, Data Warehouse & Digital Systems | BJ5: Tasks Section 12 - Customer Complaints, Accreditations & PQQ's
A6: Company / Business Unit | B6: S01 Owner | C6: S02 Owner | D6: S03 Owner | E6: S04 Owner | F6: S05 Owner | G6: S06 Owner | H6: S07 Owner | I6: S08 Owner | J6: S09 Owner | K6: S10 Owner | L6: S11 Owner | M6: S12 Owner | N6: Group HSEQ Director | O6: QA Manager | P6: Risk Register / Internal Audit | Q6: Update Task Matrix | R6: Review KEYIS Playbook | S6: ISO Audits | T6: Maintain QA File | U6: Commercial Manager | V6: Credit Insurance Renewal | W6: Review Brand Guidelines | Y6: Commercial Manager | AC6: Gas Safe Champion | AD6: F-Gas Champion | AE6: Senior Appointed Person | AI6: HV Senior Appointed Person | AL6: Commercial Manager | AM6: Credit Insurance Renewal | AQ6: Environmental Manager | AR6: Health & Safety Manager | AU6: HR Manager | AV6: Apprentice Champion | AW6: HR Manager | AX6: Health & Safety Manager | AZ6: QA Manager | BA6: Data Protection Officer

Sheet Task Definitions
A1: Task Header | B1: Procedure Area | C1: Task Description | D1: Default Responsible Role | E1: Frequency | F1: Evidence / Record Location
A2: S01 Owner | B2: Section 01 | C2: Section owner for Introduction, Quality Management & Procedure Control | D2: Named section owner | E2: Ongoing | F2: Task register / QA file
A3: S02 Owner | B3: Section 02 | C3: Section owner for Sales & Marketing | D3: Named section owner | E3: Ongoing | F3: Task register / QA file
A4: S03 Owner | B4: Section 03 | C4: Section owner for Estimating & Purchasing | D4: Named section owner | E4: Ongoing | F4: Task register / QA file
A5: S04 Owner | B5: Section 04 | C5: Section owner for Design & Project Management | D5: Named section owner | E5: Ongoing | F5: Task register / QA file
A6: S05 Owner | B6: Section 05 | C6: Section owner for Manufacturing / Operations where applicable | D6: Named section owner | E6: Ongoing | F6: Task register / QA file
A7: S06 Owner | B7: Section 06 | C7: Section owner for Commercial & Accounting | D7: Named section owner | E7: Ongoing | F7: Task register / QA file
A8: S07 Owner | B8: Section 07 | C8: Section owner for Environmental, Health & Safety | D8: Named section owner | E8: Ongoing | F8: Task register / QA file
A9: S08 Owner | B9: Section 08 | C9: Section owner for HR, Apprentices & Training | D9: Named section owner | E9: Ongoing | F9: Task register / QA file
A10: S09 Owner | B10: Section 09 | C10: Section owner for Company Engineers, Subcontractors, Vehicles & Equipment | D10: Named section owner | E10: Ongoing | F10: Task register / QA file
A11: S10 Owner | B11: Section 10 | C11: Section owner for Information Technology / Data Protection | D11: Named section owner | E11: Ongoing | F11: Task register / QA file
A12: S11 Owner | B12: Section 11 | C12: Section owner for Software / Digital Systems / Data Warehouse | D12: Named section owner | E12: Ongoing | F12: Task register / QA file
... A53: PQQs | B53: PQQs | C53: Maintain PQQ responses, supporting information and company evidence | D53: Commercial / QA | E53: As required | F53: PQQ folder

Sheet Dashboard
A1: KEYIS Task Allocation Dashboard
A3: Metric | B3: Formula / Value | D3: Company / Business Unit | E3: Allocated | F3: Blank / To Allocate
A4: Companies listed | B4: =COUNTA('Company Task Register'!A7:A22) -> 0 | D4: ='Company Task Register'!A7 -> 0 | E4: =COUNTA('Company Task Register'!B7:AY7)-COUNTIF('Company Task Register'!B7:AY7,"N/A") -> 0 | F4: =COUNTBLANK('Company Task Register'!B7:AY7) -> 50
A5: Task columns | B5: 52 | D5: ='Company Task Register'!A8 -> 0 | E5: =COUNTA('Company Task Register'!B8:AY8)-COUNTIF('Company Task Register'!B8:AY8,"N/A") -> 0 | F5: =COUNTBLANK('Company Task Register'!B8:AY8) -> 50
A6: Total allocation cells | B6: =B4*B5 -> 0 | D6: ='Company Task Register'!A9 -> 0 | E6: =COUNTA('Company Task Register'!B9:AY9)-COUNTIF('Company Task Register'!B9:AY9,"N/A") -> 0 | F6: =COUNTBLANK('Company Task Register'!B9:AY9) -> 50
A7: Allocated cells | B7: =COUNTA('Company Task Register'!B7:AY22)-COUNTIF('Company Task Register'!B7:AY22,"N/A") -> 0 | D7: ='Company Task Register'!A10 -> 0 | E7: =COUNTA('Company Task Register'!B10:AY10)-COUNTIF('Company Task Register'!B10:AY10,"N/A") -> 0 | F7: =COUNTBLANK('Company Task Register'!B10:AY10) -> 50
A8: N/A cells | B8: =COUNTIF('Company Task Register'!B7:AY22,"N/A") -> 0 | D8: ='Company Task Register'!A11 -> 0 | E8: =COUNTA('Company Task Register'!B11:AY11)-COUNTIF('Company Task Register'!B11:AY11,"N/A") -> 0 | F8: =COUNTBLANK('Company Task Register'!B11:AY11) -> 50
A9: Blank cells | B9: =B6-B7-B8 -> 0 | D9: ='Company Task Register'!A12 -> 0 | E9: =COUNTA('Company Task Register'!B12:AY12)-COUNTIF('Company Task Register'!B12:AY12,"N/A") -> 0 | F9: =COUNTBLANK('Company Task Register'!B12:AY12) -> 50
A10: Allocation complete % | B10: =IF(B6=0,0,B7/B6) -> 0 | D10: ='Company Task Register'!A13 -> 0 | E10: =COUNTA('Company Task Register'!B13:AY13)-COUNTIF('Company Task Register'!B13:AY13,"N/A") -> 0 | F10: =COUNTBLANK('Company Task Register'!B13:AY13) -> 50
D11: ='Company Task Register'!A14 -> 0 | E11: =COUNTA('Company Task Register'!B14:AY14)-COUNTIF('Company Task Register'!B14:AY14,"N/A") -> 0 | F11: =COUNTBLANK('Company Task Register'!B14:AY14) -> 50
D12: ='Company Task Register'!A15 -> 0 | E12: =COUNTA('Company Task Register'!B15:AY15)-COUNTIF('Company Task Register'!B15:AY15,"N/A") -> 0 | F12: =COUNTBLANK('Company Task Register'!B15:AY15) -> 50
D13: ='Company Task Register'!A16 -> 0 | E13: =COUNTA('Company Task Register'!B16:AY16)-COUNTIF('Company Task Register'!B16:AY16,"N/A") -> 0 | F13: =COUNTBLANK('Company Task Register'!B16:AY16) -> 50
D14: ='Company Task Register'!A17 -> 0 | E14: =COUNTA('Company Task Register'!B17:AY17)-COUNTIF('Company Task Register'!B17:AY17,"N/A") -> 0 | F14: =COUNTBLANK('Company Task Register'!B17:AY17) -> 50
D15: ='Company Task Register'!A18 -> 0 | E15: =COUNTA('Company Task Register'!B18:AY18)-COUNTIF('Company Task Register'!B18:AY18,"N/A") -> 0 | F15: =COUNTBLANK('Company Task Register'!B18:AY18) -> 50
D16: ='Company Task Register'!A19 -> 0 | E16: =COUNTA('Company Task Register'!B19:AY19)-COUNTIF('Company Task Register'!B19:AY19,"N/A") -> 0 | F16: =COUNTBLANK('Company Task Register'!B19:AY19) -> 50
D17: ='Company Task Register'!A20 -> 0 | E17: =COUNTA('Company Task Register'!B20:AY20)-COUNTIF('Company Task Register'!B20:AY20,"N/A") -> 0 | F17: =COUNTBLANK('Company Task Register'!B20:AY20) -> 50
D18: ='Company Task Register'!A21 -> 0 | E18: =COUNTA('Company Task Register'!B21:AY21)-COUNTIF('Company Task Register'!B21:AY21,"N/A") -> 0 | F18: =COUNTBLANK('Company Task Register'!B21:AY21) -> 50
D19: ='Company Task Register'!A22 -> 0 | E19: =COUNTA('Company Task Register'!B22:AY22)-COUNTIF('Company Task Register'!B22:AY22,"N/A") -> 0 | F19: =COUNTBLANK('Company Task Register'!B22:AY22) -> 50

Sheet Guidance
A1: Topic | B1: Guidance
A2: Purpose | B2: This workbook is designed for a meeting-style allocation review. Companies are listed down the left-hand side and tasks run across the top. Each cell should contain the named person responsible for that task in that company.
A3: How to use | B3: Replace the company placeholders with actual companies/business units. Then work left to right and enter the named person responsible for each task.
A4: N/A | B4: Use N/A where a task does not apply to that company. The dashboard excludes N/A from allocated counts.
A5: Section owners | B5: The first set of columns captures the owner of each procedure section. These people must review their section twice per annum and raise required changes through procedure control.
A6: Evidence | B6: Use the Task Definitions sheet to see the default evidence or record location for each task.
A7: Review frequency | B7: The Task Definitions sheet lists the suggested frequency. Amend these if the procedure requires different timing for a specific company.
A8: Filtering | B8: This is designed to be filtered manually by company/business unit and reviewed across the row.
A9: Meeting output | B9: At the end of the review, each task should have a named person or N/A for each company.
